cmsip/__init__.py
cmsip/cmsip.py
cmsip/R/chisq.R
cmsip/R/gtest.R
cmsip/R/nbtest.R
cmsip/R/nbtest_sf.R
cmsip/R/p.adj.R
cmsip/R/ttest.R
cmsip/perl/removeCommonRead.pl
cmsip-0.0.3.0.dist-info/LICENSE
cmsip-0.0.3.0.dist-info/METADATA
cmsip-0.0.3.0.dist-info/WHEEL
cmsip-0.0.3.0.dist-info/entry_points.txt
cmsip-0.0.3.0.dist-info/top_level.txt
cmsip-0.0.3.0.dist-info/RECORD
