Metadata-Version: 2.1
Name: cmsip
Version: 0.0.3.0
Summary: UNKNOWN
Home-page: https://github.com/lijinbio/cmsip
Author: Jin Li
Author-email: lijin.abc@gmail.com
License: License :: OSI Approved :: MIT License
Platform: UNKNOWN
Classifier: Programming Language :: Python :: 3
Requires-Python: >=3.6
Requires-Dist: pyyaml
Requires-Dist: matplotlib
Requires-Dist: pandas
